xbrowser_automation/__init__.py
xbrowser_automation/__main__.py
xbrowser_automation/test/__init__.py
xbrowser_automation/test/conftest.py
xbrowser_automation/test/test_app.py
xbrowser_automation-0.0.1.dist-info/METADATA
xbrowser_automation-0.0.1.dist-info/WHEEL
xbrowser_automation-0.0.1.dist-info/entry_points.txt
xbrowser_automation-0.0.1.dist-info/RECORD
