Metadata-Version: 2.1
Name: xbrowser_automation
Version: 0.0.1
Summary: xbrowser gui
Project-URL: repository, https://git.benteler.net/czirala/xbrowser_automation
Project-URL: Bug Tracker, https://git.benteler.net/czirala/xbrowser_automation/-/issues
Author-email: László Czirák <laszloii.czirak@benteler.com>
Requires-Python: >=3.9
Requires-Dist: ipykernel
Requires-Dist: voila
Provides-Extra: test
Requires-Dist: nbconvert; extra == 'test'
Requires-Dist: nbformat; extra == 'test'
Requires-Dist: pytest; extra == 'test'
Requires-Dist: pytest-cov; extra == 'test'
